signet_verify.py
signet_verify-1.0.0.dist-info/METADATA
signet_verify-1.0.0.dist-info/WHEEL
signet_verify-1.0.0.dist-info/entry_points.txt
signet_verify-1.0.0.dist-info/top_level.txt
signet_verify-1.0.0.dist-info/RECORD
