Metadata-Version: 2.4
Name: signet-verify
Version: 1.0.0
Summary: Signet Protocol - Python Verification SDK
Home-page: https://github.com/odin-protocol/signet-protocol
Author: ODIN Protocol Corporation
Author-email: support@odinprotocol.com
License: Apache License 2.0
Project-URL: Documentation, https://github.com/odin-protocol/signet-protocol/docs
Project-URL: Source, https://github.com/odin-protocol/signet-protocol
Project-URL: Tracker, https://github.com/odin-protocol/signet-protocol/issues
Keywords: signet protocol verification cryptography receipts blockchain audit
Classifier: Development Status :: 5 - Production/Stable
Classifier: Intended Audience :: Developers
Classifier: License :: OSI Approved :: Apache Software License
Classifier: Operating System :: OS Independent
Classifier: Programming Language :: Python :: 3
Classifier: Programming Language :: Python :: 3.7
Classifier: Programming Language :: Python :: 3.8
Classifier: Programming Language :: Python :: 3.9
Classifier: Programming Language :: Python :: 3.10
Classifier: Programming Language :: Python :: 3.11
Classifier: Topic :: Security :: Cryptography
Classifier: Topic :: Software Development :: Libraries :: Python Modules
Classifier: Topic :: Internet :: WWW/HTTP
Requires-Python: >=3.7
Requires-Dist: cryptography>=3.0.0
Requires-Dist: requests>=2.25.0
Provides-Extra: dev
Requires-Dist: pytest>=6.0.0; extra == "dev"
Requires-Dist: pytest-cov>=2.10.0; extra == "dev"
Requires-Dist: black>=21.0.0; extra == "dev"
Requires-Dist: flake8>=3.8.0; extra == "dev"
Provides-Extra: test
Requires-Dist: pytest>=6.0.0; extra == "test"
Requires-Dist: pytest-asyncio>=0.18.0; extra == "test"
Dynamic: author
Dynamic: author-email
Dynamic: classifier
Dynamic: description
Dynamic: description-content-type
Dynamic: home-page
Dynamic: keywords
Dynamic: license
Dynamic: project-url
Dynamic: provides-extra
Dynamic: requires-dist
Dynamic: requires-python
Dynamic: summary
